global_mapping/__init__.py
global_mapping/battlebit.py
global_mapping/battlelog.py
global_mapping/bf1.py
global_mapping/bf1942.py
global_mapping/bf2.py
global_mapping/bf2042.py
global_mapping/bf2142.py
global_mapping/bf3.py
global_mapping/bf4.py
global_mapping/bf5.py
global_mapping/bf6.py
global_mapping/bfbc2.py
global_mapping/bfh.py
global_mapping/bfvietnam.py
global_mapping/marne.py
global_mapping/other.py
global_mapping/readability/bf2042/languages/settingValues/ar_sa.py
global_mapping/readability/bf2042/languages/settingValues/de_de.py
global_mapping/readability/bf2042/languages/settingValues/en_us.py
global_mapping/readability/bf2042/languages/settingValues/es_es.py
global_mapping/readability/bf2042/languages/settingValues/es_mx.py
global_mapping/readability/bf2042/languages/settingValues/fr_fr.py
global_mapping/readability/bf2042/languages/settingValues/it_it.py
global_mapping/readability/bf2042/languages/settingValues/ja_jp.py
global_mapping/readability/bf2042/languages/settingValues/ko_kr.py
global_mapping/readability/bf2042/languages/settingValues/main.py
global_mapping/readability/bf2042/languages/settingValues/pl_pl.py
global_mapping/readability/bf2042/languages/settingValues/pt_br.py
global_mapping/readability/bf2042/languages/settingValues/ru_ru.py
global_mapping/readability/bf2042/languages/settingValues/zh_cn.py
global_mapping/readability/bf2042/languages/settingValues/zh_tw.py
global_mapping/readability/bf2042/main.py
global_mapping/readability/bf2042/saved_items/__init__.py
global_mapping/readability/bf2042/saved_items/progresstion_types.py
global_mapping/readability/bf2042/saved_items/singleton.py
global_mapping/readability/bf6.py
global_mapping/readability/bfv.py
global_mapping/readability/exceptions.py
global_mapping/readability/shared.py
gametools_global_mapping-0.1.40.dist-info/METADATA
gametools_global_mapping-0.1.40.dist-info/WHEEL
gametools_global_mapping-0.1.40.dist-info/RECORD
