Metadata-Version: 2.4
Name: gametools-global-mapping
Version: 0.1.40
Summary: A repo that contains all mapping required by GameTools
License: MIT
Author: p0lygun
Author-email: solankivibhakar82@gmail.com
Requires-Python: >=3.12,<4.0
Classifier: License :: OSI Approved :: MIT License
Classifier: Programming Language :: Python :: 3
Classifier: Programming Language :: Python :: 3.12
Classifier: Programming Language :: Python :: 3.13
Classifier: Programming Language :: Python :: 3.14
Requires-Dist: requests (>=2.31.0,<3.0.0)
